_MeCab.cp36-win_amd64.pyd
eunjeon/__init__.py
eunjeon/_mecab.py
eunjeon/constants.py
eunjeon/mecab.py
eunjeon/data/char.bin
eunjeon/data/char.def
eunjeon/data/dicrc
eunjeon/data/feature.def
eunjeon/data/left-id.def
eunjeon/data/libmecab.dll
eunjeon/data/matrix.bin
eunjeon/data/mecab-cost-train.exe
eunjeon/data/mecab-dict-gen.exe
eunjeon/data/mecab-dict-index.exe
eunjeon/data/mecab-system-eval.exe
eunjeon/data/mecab-test-gen.exe
eunjeon/data/mecab.exe
eunjeon/data/mecabrc
eunjeon/data/model.bin
eunjeon/data/pos-id.def
eunjeon/data/rewrite.def
eunjeon/data/right-id.def
eunjeon/data/sys.dic
eunjeon/data/unk.def
eunjeon/data/unk.dic
eunjeon/data/sdk/libmecab.lib
eunjeon/data/sdk/mecab-cost-train.lib
eunjeon/data/sdk/mecab-dict-gen.lib
eunjeon/data/sdk/mecab-dict-index.lib
eunjeon/data/sdk/mecab-system-eval.lib
eunjeon/data/sdk/mecab-test-gen.lib
eunjeon/data/sdk/mecab.h
eunjeon/data/sdk/mecab.lib
eunjeon-0.4.0.dist-info/DESCRIPTION.rst
eunjeon-0.4.0.dist-info/METADATA
eunjeon-0.4.0.dist-info/RECORD
eunjeon-0.4.0.dist-info/WHEEL
eunjeon-0.4.0.dist-info/entry_points.txt
eunjeon-0.4.0.dist-info/metadata.json
eunjeon-0.4.0.dist-info/top_level.txt
